gamey/__init__.py
gamey-0.7.dist-info/METADATA
gamey-0.7.dist-info/WHEEL
gamey-0.7.dist-info/RECORD
